dxnesici/__init__.py
dxnesici/alg.py
dxnesici-1.0.4.dist-info/LICENSE
dxnesici-1.0.4.dist-info/METADATA
dxnesici-1.0.4.dist-info/WHEEL
dxnesici-1.0.4.dist-info/top_level.txt
dxnesici-1.0.4.dist-info/RECORD
